<?xml version="1.0"?>
<!-- This file is part of trytond-cash_bank_reconciliation module. The COPYRIGHT file at the top level of
this repository contains the full copyright notices and license terms. -->
<tree editable="bottom">
    <field name="reconciliation"/>
    <field name="date"/>
    <field name="receipt"/>
    <field name="move_description"/>
    <field name="description"/>
    <field name="effective_date"/>
    <field name="amount"/>
    <field name="check"/>
    <field name="comment"/>
</tree>
